Metadata-Version: 2.1
Name: ninsolver
Version: 0.3
Summary: library for solving captchas using https://api.api-ninjas.com/v1
Home-page: UNKNOWN
Author-email: bonnita1900432@gmail.com
License: UNKNOWN
Platform: UNKNOWN
